xrpy/__init__.py
xrpy/constants.py
xrpy/deprecated.py
xrpy/main.py
xrpy-0.2.1.dist-info/METADATA
xrpy-0.2.1.dist-info/WHEEL
xrpy-0.2.1.dist-info/top_level.txt
xrpy-0.2.1.dist-info/RECORD
