Metadata-Version: 2.1
Name: xrpy
Version: 0.2.1
Summary: Easier XRPL functions
Home-page: https://github.com/amiwrpremium/xrpy
Author: amiwrpremium
Author-email: amiwrpremium@gmail.com
License: MIT
Project-URL: Bug Tracker, https://github.com/amiwrpremium/xrpy/issues
Keywords: xrp,xrpl,ledger,blockchain,ripple,rippled,SDK
Platform: UNKNOWN
Classifier: Development Status :: 3 - Alpha
Classifier: Intended Audience :: Developers
Classifier: Topic :: Software Development :: Build Tools
Classifier: License :: OSI Approved :: MIT License
Classifier: Programming Language :: Python :: 3
Classifier: Programming Language :: Python :: 3.4
Classifier: Programming Language :: Python :: 3.5
Classifier: Programming Language :: Python :: 3.6
Classifier: Programming Language :: Python :: 3.7
Classifier: Programming Language :: Python :: 3.8
Classifier: Programming Language :: Python :: 3.9
Requires-Python: >=3.8
Requires-Dist: xrpl-py
Requires-Dist: deprecation
